enwheel/__init__.py
enwheel/cli.py
enwheel/git.py
enwheel/html.py
enwheel/server.py
enwheel-1.1.0.dist-info/DESCRIPTION.rst
enwheel-1.1.0.dist-info/METADATA
enwheel-1.1.0.dist-info/RECORD
enwheel-1.1.0.dist-info/WHEEL
enwheel-1.1.0.dist-info/entry_points.txt
enwheel-1.1.0.dist-info/metadata.json
enwheel-1.1.0.dist-info/top_level.txt
