Metadata-Version: 2.0
Name: enwheel
Version: 1.1.0
Summary: get wheels, generate repo
Home-page: UNKNOWN
Author: CFPB
Author-email: tech@cfpb.gov
License: Public Domain, CC0
Platform: UNKNOWN
Classifier: Topic :: Internet :: WWW/HTTP :: Dynamic Content
Classifier: Intended Audience :: Developers
Classifier: Programming Language :: Python
Classifier: Programming Language :: Python :: 2.6
Classifier: Programming Language :: Python :: 2.7
Classifier: Development Status :: 4 - Beta
Classifier: Operating System :: OS Independent
Requires-Dist: docopt (==0.6.2)
Requires-Dist: pip
Requires-Dist: semver
Requires-Dist: wheel
